ape_huff/__init__.py
ape_huff/compiler.py
ape_huff-0.1.2.dist-info/LICENSE
ape_huff-0.1.2.dist-info/METADATA
ape_huff-0.1.2.dist-info/WHEEL
ape_huff-0.1.2.dist-info/top_level.txt
ape_huff-0.1.2.dist-info/RECORD
