Metadata-Version: 2.1
Name: ape-huff
Version: 0.1.2
Summary: Huff compiler plugin for the eth-ape development framework
Author: 0xcefa1090d
License: MIT License
Project-URL: Homepage, https://github.com/0xcefa1090d/ape-huff
Requires-Python: >=3.10
Provides-Extra: dev
License-File: LICENSE
